Metadata-Version: 2.1
Name: ColabGitlabSetup
Version: 0.0.3
Summary: A simple API for linking Google Colab Notebooks to Gitlab using SSH
Home-page: https://github.com/LaurenceMolloy/colab_gitlab_setup
Author: Laurence Molloy
Author-email: laurence.molloy@gmail.com
License: MIT
Keywords: colaboratory colab gitlab ssh
Platform: UNKNOWN
Classifier: Development Status :: 3 - Alpha
Classifier: Programming Language :: Python :: 3
Classifier: License :: OSI Approved :: MIT License
Classifier: Operating System :: OS Independent
Requires-Python: >=3.6
License-File: LICENSE
